Metadata-Version: 2.1
Name: dffml-model-transformers
Version: 0.0.3
Summary: UNKNOWN
Home-page: https://github.com/intel/dffml/blob/master/model/transformers/README.md
Author: Himanshu Tripathi
Author-email: himanshutripathi366@gmail.com
License: MIT
Platform: UNKNOWN
Classifier: Development Status :: 3 - Alpha
Classifier: Intended Audience :: Developers
Classifier: License :: OSI Approved :: MIT License
Classifier: License :: OSI Approved :: Apache Software License
Classifier: Natural Language :: English
Classifier: Operating System :: OS Independent
Classifier: Programming Language :: Python :: 3 :: Only
Classifier: Programming Language :: Python :: 3.7
Classifier: Programming Language :: Python :: Implementation :: CPython
Classifier: Programming Language :: Python :: Implementation :: PyPy
